{
    "type": "object",
    "properties": {
        "id": {
            "type": "string"
        },
        "name": {
            "type": "string"
        },
        "description": {
            "type": "null"
        },
        "total": {
            "type": "string"
        },
        "created": {
            "type": "string"
        },
        "updated": {
            "type": ["null", "string"]
        }
    },
    "required": [
        "id",
        "name",
        "description",
        "total",
        "created",
        "updated"
    ]
}
