{
    "$id": "https://api.costs-to-expect.com/v2/api/schema/auth/options/update-profile.json",
    "type": "object",
    "properties": {
        "POST": {
            "type": "object",
            "properties": {
                "description": {
                    "type": "string"
                },
                "authentication": {
                    "type": "object",
                    "properties": {
                        "required": {
                            "type": "boolean"
                        },
                        "authenticated": {
                            "type": "boolean"
                        }
                    }
                },
                "fields": {
                    "type": "object",
                    "properties": {
                        "name": {
                            "type": "object",
                            "properties": {
                                "field": {
                                    "type": "string"
                                },
                                "title": {
                                    "type": "string"
                                },
                                "description": {
                                    "type": "string"
                                },
                                "type": {
                                    "type": "string"
                                },
                                "required": {
                                    "type": "boolean"
                                }
                            }
                        },
                        "email": {
                            "type": "object",
                            "properties": {
                                "field": {
                                    "type": "string"
                                },
                                "title": {
                                    "type": "string"
                                },
                                "description": {
                                    "type": "string"
                                },
                                "type": {
                                    "type": "string"
                                },
                                "required": {
                                    "type": "boolean"
                                }
                            }
                        }
                    },
                    "required": [
                        "name",
                        "email"
                    ]
                }
            },
            "required": [
                "description",
                "authentication",
                "fields"
            ]
        }
    },
    "required": [
        "POST"
    ]
}
