{
    "$id": "https://api.costs-to-expect.com/v2/api/schema/options/allocated-expense-collection.json",
    "type": "object",
    "properties": {
        "GET": {
            "type": "object",
            "properties": {
                "description": {
                    "type": "string"
                },
                "authentication": {
                    "type": "object",
                    "properties": {
                        "required": {
                            "type": "boolean"
                        },
                        "authenticated": {
                            "type": "boolean"
                        }
                    },
                    "required": [
                        "required",
                        "authenticated"
                    ]
                },
                "sortable": {
                    "type": "array",
                    "items": {
                        "type": "string"
                    }
                },
                "searchable": {
                    "type": "object",
                    "properties": {
                        "name": {
                            "type": "object",
                            "properties": {
                                "type": {
                                    "type": "string"
                                }
                            }
                        },
                        "description": {
                            "type": "object",
                            "properties": {
                                "type": {
                                    "type": "string"
                                }
                            }
                        }
                    },
                    "required": [
                        "name",
                        "description"
                    ]
                },
                "filterable": {
                    "type": "object",
                    "properties": {
                        "effective_date": {
                            "type": "object",
                            "properties": {
                                "type": {
                                    "type": "string"
                                }
                            }
                        },
                        "total": {
                            "type": "object",
                            "properties": {
                                "type": {
                                    "type": "string"
                                }
                            }
                        },
                        "actualised_total": {
                            "type": "object",
                            "properties": {
                                "type": {
                                    "type": "string"
                                }
                            }
                        }
                    }
                },
                "parameters": {
                    "type":"object",
                    "properties": {
                        "offset": {
                            "type": "object",
                            "properties": {
                                "parameter": {
                                    "type": "string"
                                },
                                "title": {
                                    "type": "string"
                                },
                                "description": {
                                    "type": "string"
                                },
                                "default": {
                                    "type": "integer"
                                },
                                "type": {
                                    "type": "string"
                                },
                                "required": {
                                    "type": "boolean"
                                }
                            },
                            "required": [
                                "parameter",
                                "title",
                                "description",
                                "default",
                                "type",
                                "required"
                            ]
                        },
                        "limit": {
                            "type": "object",
                            "properties": {
                                "parameter": {
                                    "type": "string"
                                },
                                "title": {
                                    "type": "string"
                                },
                                "description": {
                                    "type": "string"
                                },
                                "default": {
                                    "type": "integer"
                                },
                                "type": {
                                    "type": "string"
                                },
                                "required": {
                                    "type": "boolean"
                                }
                            },
                            "required": [
                                "parameter",
                                "title",
                                "description",
                                "default",
                                "type",
                                "required"
                            ]
                        },
                        "sort": {
                            "type": "object",
                            "properties": {
                                "parameter": {
                                    "type": "string"
                                },
                                "title": {
                                    "type": "string"
                                },
                                "description": {
                                    "type": "string"
                                },
                                "default": {
                                    "type": "null"
                                },
                                "type": {
                                    "type": "string"
                                },
                                "required": {
                                    "type": "boolean"
                                }
                            },
                            "required": [
                                "parameter",
                                "title",
                                "description",
                                "default",
                                "type",
                                "required"
                            ]
                        },
                        "search": {
                            "type": "object",
                            "properties": {
                                "parameter": {
                                    "type": "string"
                                },
                                "title": {
                                    "type": "string"
                                },
                                "description": {
                                    "type": "string"
                                },
                                "default": {
                                    "type": "null"
                                },
                                "type": {
                                    "type": "string"
                                },
                                "required": {
                                    "type": "boolean"
                                }
                            },
                            "required": [
                                "parameter",
                                "title",
                                "description",
                                "default",
                                "type",
                                "required"
                            ]
                        },
                        "filter": {
                            "type": "object",
                            "properties": {
                                "parameter": {
                                    "type": "string"
                                },
                                "title": {
                                    "type": "string"
                                },
                                "description": {
                                    "type": "string"
                                },
                                "default": {
                                    "type": "null"
                                },
                                "type": {
                                    "type": "string"
                                },
                                "required": {
                                    "type": "boolean"
                                }
                            },
                            "required": [
                                "parameter",
                                "title",
                                "description",
                                "default",
                                "type",
                                "required"
                            ]
                        },
                        "include-categories": {
                            "type": "object",
                            "properties": {
                                "parameter": {
                                    "type": "string"
                                },
                                "title": {
                                    "type": "string"
                                },
                                "description": {
                                    "type": "string"
                                },
                                "type": {
                                    "type": "string"
                                },
                                "required": {
                                    "type": "boolean"
                                }
                            },
                            "required": [
                                "parameter",
                                "title",
                                "description",
                                "type",
                                "required"
                            ]
                        },
                        "include-subcategories": {
                            "type": "object",
                            "properties": {
                                "parameter": {
                                    "type": "string"
                                },
                                "title": {
                                    "type": "string"
                                },
                                "description": {
                                    "type": "string"
                                },
                                "type": {
                                    "type": "string"
                                },
                                "required": {
                                    "type": "boolean"
                                }
                            },
                            "required": [
                                "parameter",
                                "title",
                                "description",
                                "type",
                                "required"
                            ]
                        },
                        "include-unpublished": {
                            "type": "object",
                            "properties": {
                                "parameter": {
                                    "type": "string"
                                },
                                "title": {
                                    "type": "string"
                                },
                                "description": {
                                    "type": "string"
                                },
                                "type": {
                                    "type": "string"
                                },
                                "required": {
                                    "type": "boolean"
                                }
                            },
                            "required": [
                                "parameter",
                                "title",
                                "description",
                                "type",
                                "required"
                            ]
                        },
                        "category": {
                            "type": "object",
                            "properties": {
                                "parameter": {
                                    "type": "string"
                                },
                                "title": {
                                    "type": "string"
                                },
                                "description": {
                                    "type": "string"
                                },
                                "default": {
                                    "type": ["null", "string"]
                                },
                                "type": {
                                    "type": "string"
                                },
                                "required": {
                                    "type": "boolean"
                                }
                            },
                            "required": [
                                "parameter",
                                "title",
                                "description",
                                "default",
                                "type",
                                "required"
                            ]
                        },
                        "subcategory": {
                            "type": "object",
                            "properties": {
                                "parameter": {
                                    "type": "string"
                                },
                                "title": {
                                    "type": "string"
                                },
                                "description": {
                                    "type": "string"
                                },
                                "default": {
                                    "type": ["null", "string"]
                                },
                                "type": {
                                    "type": "string"
                                },
                                "required": {
                                    "type": "boolean"
                                }
                            },
                            "required": [
                                "parameter",
                                "title",
                                "description",
                                "default",
                                "type",
                                "required"
                            ]
                        },
                        "year": {
                            "type": "object",
                            "properties": {
                                "parameter": {
                                    "type": "string"
                                },
                                "title": {
                                    "type": "string"
                                },
                                "description": {
                                    "type": "string"
                                },
                                "default": {
                                    "type": ["null", "string"]
                                },
                                "type": {
                                    "type": "string"
                                },
                                "required": {
                                    "type": "boolean"
                                }
                            },
                            "required": [
                                "parameter",
                                "title",
                                "description",
                                "default",
                                "type",
                                "required"
                            ]
                        },
                        "month": {
                            "type": "object",
                            "properties": {
                                "parameter": {
                                    "type": "string"
                                },
                                "title": {
                                    "type": "string"
                                },
                                "description": {
                                    "type": "string"
                                },
                                "default": {
                                    "type": ["null", "string"]
                                },
                                "type": {
                                    "type": "string"
                                },
                                "required": {
                                    "type": "boolean"
                                }
                            },
                            "required": [
                                "parameter",
                                "title",
                                "description",
                                "default",
                                "type",
                                "required"
                            ]
                        }
                    },
                    "required": [
                        "offset",
                        "limit",
                        "sort",
                        "search",
                        "filter",
                        "include-categories",
                        "include-subcategories",
                        "include-unpublished",
                        "category",
                        "subcategory",
                        "year",
                        "month"
                    ]
                }
            },
            "required": [
                "description",
                "authentication",
                "sortable",
                "searchable",
                "filterable",
                "parameters"
            ]
        }
    },
    "required": [
        "GET"
    ]
}
